Workbook

Sheet Analysis
A1: Category | B1: Month | C1: Amount+ | D1: Amount | E1: Transaction Type
A2: Protein | B2: 45658 | C2: 3517850 | D2: =IFS(E:E = "Expenses", C:C * -1, E:E = "Sales", C:C * 1,True,0) -> -3517850 | E2: Expenses
A3: Veggies | B3: 45658 | C3: 133400 | D3: =IFS(E:E = "Expenses", C:C * -1, E:E = "Sales", C:C * 1,True,0) -> -133400 | E3: Expenses
A4: Bread | B4: 45658 | C4: 45080 | D4: =IFS(E:E = "Expenses", C:C * -1, E:E = "Sales", C:C * 1,True,0) -> -45080 | E4: Expenses
A5: Gas | B5: 45658 | C5: 331142.5 | D5: =IFS(E:E = "Expenses", C:C * -1, E:E = "Sales", C:C * 1,True,0) -> -331142.5 | E5: Expenses
A6: Ingredients | B6: 45658 | C6: 593400 | D6: =IFS(E:E = "Expenses", C:C * -1, E:E = "Sales", C:C * 1,True,0) -> -593400 | E6: Expenses
A7: Market List | B7: 45658 | C7: 1187432.5 | D7: =IFS(E:E = "Expenses", C:C * -1, E:E = "Sales", C:C * 1,True,0) -> -1187432.5 | E7: Expenses
A8: Pepper & Co | B8: 45658 | C8: 2848849 | D8: =IFS(E:E = "Expenses", C:C * -1, E:E = "Sales", C:C * 1,True,0) -> -2848849 | E8: Expenses
A9: Salaries | B9: 45658 | C9: 770500 | D9: =IFS(E:E = "Expenses", C:C * -1, E:E = "Sales", C:C * 1,True,0) -> -770500 | E9: Expenses
A10: Rent | B10: 45658 | C10: 115000 | D10: =IFS(E:E = "Expenses", C:C * -1, E:E = "Sales", C:C * 1,True,0) -> -115000 | E10: Expenses
A11: Other Expenses | B11: 45658 | C11: 479445.35 | D11: =IFS(E:E = "Expenses", C:C * -1, E:E = "Sales", C:C * 1,True,0) -> -479445.35 | E11: Expenses
A12: Electricity | B12: 45658 | C12: 46000 | D12: =IFS(E:E = "Expenses", C:C * -1, E:E = "Sales", C:C * 1,True,0) -> -46000 | E12: Expenses
A13: Main Dish | B13: 45658 | C13: 11621923 | D13: =IFS(E:E = "Expenses", C:C * -1, E:E = "Sales", C:C * 1,True,0) -> 11621923 | E13: Sales
... A279: Drink | B279: 46101 | C279: 171292.5 | D279: =IFS(E:E = "Expenses", C:C * -1, E:E = "Sales", C:C * 1,True,0) -> 171292.5 | E279: Sales

Sheet Monthly_summary
A1: Month | B1: Sales | C1: Expenses | D1: OperationalCost | E1: CostOfSales | F1: GrossProfit | G1: NetProfit | H1: GrossMargin | I1: NetMargin
A2: 45658 | B2: =SUMIFS(Analysis!C:C, Analysis!E:E, "Sales", Analysis!B:B, ">="&A2, Analysis!B:B, "<"&EDATE(A2,1)) -> 20654862 | C2: =SUMIFS(Analysis!C:C, Analysis!E:E, "Expenses", Analysis!B:B, ">="&A2, Analysis!B:B, "<"&EDATE(A2,1)) -> 10068099 | D2: =-SUMIFS(Analysis!C:C,Analysis!B:B, ">="&A2,Analysis!B:B,"<"&EDate(A2,1), Analysis!A:A,"Electricity")-SUMIFS(Analysis!C:C,Analysis!B:B, ">="&A2,Analysis!B:B,"<"&EDate(A2,1), Analysis!A:A,"Petroleum") -SUMIFS(Analysis!C:C,Analysis!B:B, ">="&A2,Analysis!B:B,"<"&EDate(A2,1), Analysis!A:A,"rent") -SUMIFS(Analysis!C:C,Analysis!B:B, ">="&A2,Analysis!B:B,"<"&EDate(A2,1), Analysis!A:A,"salaries") -> -931500 | E2: =-SUMIFS(Analysis!C:C, Analysis!E:E,"Expenses", Analysis!B:B, ">="&A2,Analysis!B:B,"<"&EDate(A2,1), Analysis!A:A,"<>Electricity",Analysis!A:A,"<>Petroleum",Analysis!A:A,"<>rent",Analysis!A:A,"<>salaries") -> -9136599.3 | F2: =B:B +E:E -> 11518263 | G2: =F:F + D:D -> 10586763 | H2: =(F:F/B:B) -> 0.55765383 | I2: =(G:G/B:B) -> 0.51255549
A3: 45689 | B3: =SUMIFS(Analysis!C:C, Analysis!E:E, "Sales", Analysis!B:B, ">="&A3, Analysis!B:B, "<"&EDATE(A3,1)) -> 17828450 | C3: =SUMIFS(Analysis!C:C, Analysis!E:E, "Expenses", Analysis!B:B, ">="&A3, Analysis!B:B, "<"&EDATE(A3,1)) -> 9178495 | D3: =-SUMIFS(Analysis!C:C,Analysis!B:B, ">="&A3,Analysis!B:B,"<"&EDate(A3,1), Analysis!A:A,"Electricity")-SUMIFS(Analysis!C:C,Analysis!B:B, ">="&A3,Analysis!B:B,"<"&EDate(A3,1), Analysis!A:A,"Petroleum") -SUMIFS(Analysis!C:C,Analysis!B:B, ">="&A3,Analysis!B:B,"<"&EDate(A3,1), Analysis!A:A,"rent") -SUMIFS(Analysis!C:C,Analysis!B:B, ">="&A3,Analysis!B:B,"<"&EDate(A3,1), Analysis!A:A,"salaries") -> -816500 | E3: =-SUMIFS(Analysis!C:C, Analysis!E:E,"Expenses", Analysis!B:B, ">="&A3,Analysis!B:B,"<"&EDate(A3,1), Analysis!A:A,"<>Electricity",Analysis!A:A,"<>Petroleum",Analysis!A:A,"<>rent",Analysis!A:A,"<>salaries") -> -8361995 | F3: =B:B +E:E -> 9466455 | G3: =F:F + D:D -> 8649955 | H3: =(F:F/B:B) -> 0.53097465 | I3: =(G:G/B:B) -> 0.48517706
A4: 45717 | B4: =SUMIFS(Analysis!C:C, Analysis!E:E, "Sales", Analysis!B:B, ">="&A4, Analysis!B:B, "<"&EDATE(A4,1)) -> 15026992 | C4: =SUMIFS(Analysis!C:C, Analysis!E:E, "Expenses", Analysis!B:B, ">="&A4, Analysis!B:B, "<"&EDATE(A4,1)) -> 9062393.3 | D4: =-SUMIFS(Analysis!C:C,Analysis!B:B, ">="&A4,Analysis!B:B,"<"&EDate(A4,1), Analysis!A:A,"Electricity")-SUMIFS(Analysis!C:C,Analysis!B:B, ">="&A4,Analysis!B:B,"<"&EDate(A4,1), Analysis!A:A,"Petroleum") -SUMIFS(Analysis!C:C,Analysis!B:B, ">="&A4,Analysis!B:B,"<"&EDate(A4,1), Analysis!A:A,"rent") -SUMIFS(Analysis!C:C,Analysis!B:B, ">="&A4,Analysis!B:B,"<"&EDate(A4,1), Analysis!A:A,"salaries") -> -816500 | E4: =-SUMIFS(Analysis!C:C, Analysis!E:E,"Expenses", Analysis!B:B, ">="&A4,Analysis!B:B,"<"&EDate(A4,1), Analysis!A:A,"<>Electricity",Analysis!A:A,"<>Petroleum",Analysis!A:A,"<>rent",Analysis!A:A,"<>salaries") -> -8245893.3 | F4: =B:B +E:E -> 6781099.2 | G4: =F:F + D:D -> 5964599.2 | H4: =(F:F/B:B) -> 0.45126124 | I4: =(G:G/B:B) -> 0.39692568
A5: 45748 | B5: =SUMIFS(Analysis!C:C, Analysis!E:E, "Sales", Analysis!B:B, ">="&A5, Analysis!B:B, "<"&EDATE(A5,1)) -> 13758945 | C5: =SUMIFS(Analysis!C:C, Analysis!E:E, "Expenses", Analysis!B:B, ">="&A5, Analysis!B:B, "<"&EDATE(A5,1)) -> 9411174.5 | D5: =-SUMIFS(Analysis!C:C,Analysis!B:B, ">="&A5,Analysis!B:B,"<"&EDate(A5,1), Analysis!A:A,"Electricity")-SUMIFS(Analysis!C:C,Analysis!B:B, ">="&A5,Analysis!B:B,"<"&EDate(A5,1), Analysis!A:A,"Petroleum") -SUMIFS(Analysis!C:C,Analysis!B:B, ">="&A5,Analysis!B:B,"<"&EDate(A5,1), Analysis!A:A,"rent") -SUMIFS(Analysis!C:C,Analysis!B:B, ">="&A5,Analysis!B:B,"<"&EDate(A5,1), Analysis!A:A,"salaries") -> -759000 | E5: =-SUMIFS(Analysis!C:C, Analysis!E:E,"Expenses", Analysis!B:B, ">="&A5,Analysis!B:B,"<"&EDate(A5,1), Analysis!A:A,"<>Electricity",Analysis!A:A,"<>Petroleum",Analysis!A:A,"<>rent",Analysis!A:A,"<>salaries") -> -8652174.5 | F5: =B:B +E:E -> 5106770.5 | G5: =F:F + D:D -> 4347770.5 | H5: =(F:F/B:B) -> 0.37116003 | I5: =(G:G/B:B) -> 0.31599592
A6: 45778 | B6: =SUMIFS(Analysis!C:C, Analysis!E:E, "Sales", Analysis!B:B, ">="&A6, Analysis!B:B, "<"&EDATE(A6,1)) -> 15133828 | C6: =SUMIFS(Analysis!C:C, Analysis!E:E, "Expenses", Analysis!B:B, ">="&A6, Analysis!B:B, "<"&EDATE(A6,1)) -> 9623464.5 | D6: =-SUMIFS(Analysis!C:C,Analysis!B:B, ">="&A6,Analysis!B:B,"<"&EDate(A6,1), Analysis!A:A,"Electricity")-SUMIFS(Analysis!C:C,Analysis!B:B, ">="&A6,Analysis!B:B,"<"&EDate(A6,1), Analysis!A:A,"Petroleum") -SUMIFS(Analysis!C:C,Analysis!B:B, ">="&A6,Analysis!B:B,"<"&EDate(A6,1), Analysis!A:A,"rent") -SUMIFS(Analysis!C:C,Analysis!B:B, ">="&A6,Analysis!B:B,"<"&EDate(A6,1), Analysis!A:A,"salaries") -> -759000 | E6: =-SUMIFS(Analysis!C:C, Analysis!E:E,"Expenses", Analysis!B:B, ">="&A6,Analysis!B:B,"<"&EDate(A6,1), Analysis!A:A,"<>Electricity",Analysis!A:A,"<>Petroleum",Analysis!A:A,"<>rent",Analysis!A:A,"<>salaries") -> -8864464.5 | F6: =B:B +E:E -> 6269363 | G6: =F:F + D:D -> 5510363 | H6: =(F:F/B:B) -> 0.41426156 | I6: =(G:G/B:B) -> 0.36410901
A7: 45809 | B7: =SUMIFS(Analysis!C:C, Analysis!E:E, "Sales", Analysis!B:B, ">="&A7, Analysis!B:B, "<"&EDATE(A7,1)) -> 15133828 | C7: =SUMIFS(Analysis!C:C, Analysis!E:E, "Expenses", Analysis!B:B, ">="&A7, Analysis!B:B, "<"&EDATE(A7,1)) -> 10471336 | D7: =-SUMIFS(Analysis!C:C,Analysis!B:B, ">="&A7,Analysis!B:B,"<"&EDate(A7,1), Analysis!A:A,"Electricity")-SUMIFS(Analysis!C:C,Analysis!B:B, ">="&A7,Analysis!B:B,"<"&EDate(A7,1), Analysis!A:A,"Petroleum") -SUMIFS(Analysis!C:C,Analysis!B:B, ">="&A7,Analysis!B:B,"<"&EDate(A7,1), Analysis!A:A,"rent") -SUMIFS(Analysis!C:C,Analysis!B:B, ">="&A7,Analysis!B:B,"<"&EDate(A7,1), Analysis!A:A,"salaries") -> -799250 | E7: =-SUMIFS(Analysis!C:C, Analysis!E:E,"Expenses", Analysis!B:B, ">="&A7,Analysis!B:B,"<"&EDate(A7,1), Analysis!A:A,"<>Electricity",Analysis!A:A,"<>Petroleum",Analysis!A:A,"<>rent",Analysis!A:A,"<>salaries") -> -9672086.5 | F7: =B:B +E:E -> 5461741 | G7: =F:F + D:D -> 4662491 | H7: =(F:F/B:B) -> 0.36089621 | I7: =(G:G/B:B) -> 0.30808406
A8: 45839 | B8: =SUMIFS(Analysis!C:C, Analysis!E:E, "Sales", Analysis!B:B, ">="&A8, Analysis!B:B, "<"&EDATE(A8,1)) -> 16100000 | C8: =SUMIFS(Analysis!C:C, Analysis!E:E, "Expenses", Analysis!B:B, ">="&A8, Analysis!B:B, "<"&EDATE(A8,1)) -> 12474614 | D8: =-SUMIFS(Analysis!C:C,Analysis!B:B, ">="&A8,Analysis!B:B,"<"&EDate(A8,1), Analysis!A:A,"Electricity")-SUMIFS(Analysis!C:C,Analysis!B:B, ">="&A8,Analysis!B:B,"<"&EDate(A8,1), Analysis!A:A,"Petroleum") -SUMIFS(Analysis!C:C,Analysis!B:B, ">="&A8,Analysis!B:B,"<"&EDate(A8,1), Analysis!A:A,"rent") -SUMIFS(Analysis!C:C,Analysis!B:B, ">="&A8,Analysis!B:B,"<"&EDate(A8,1), Analysis!A:A,"salaries") -> -799250 | E8: =-SUMIFS(Analysis!C:C, Analysis!E:E,"Expenses", Analysis!B:B, ">="&A8,Analysis!B:B,"<"&EDate(A8,1), Analysis!A:A,"<>Electricity",Analysis!A:A,"<>Petroleum",Analysis!A:A,"<>rent",Analysis!A:A,"<>salaries") -> -11675364 | F8: =B:B +E:E -> 4424636.5 | G8: =F:F + D:D -> 3625386.5 | H8: =(F:F/B:B) -> 0.27482214 | I8: =(G:G/B:B) -> 0.22517929
A9: 45870 | B9: =SUMIFS(Analysis!C:C, Analysis!E:E, "Sales", Analysis!B:B, ">="&A9, Analysis!B:B, "<"&EDATE(A9,1)) -> 16289808 | C9: =SUMIFS(Analysis!C:C, Analysis!E:E, "Expenses", Analysis!B:B, ">="&A9, Analysis!B:B, "<"&EDATE(A9,1)) -> 10108799 | D9: =-SUMIFS(Analysis!C:C,Analysis!B:B, ">="&A9,Analysis!B:B,"<"&EDate(A9,1), Analysis!A:A,"Electricity")-SUMIFS(Analysis!C:C,Analysis!B:B, ">="&A9,Analysis!B:B,"<"&EDate(A9,1), Analysis!A:A,"Petroleum") -SUMIFS(Analysis!C:C,Analysis!B:B, ">="&A9,Analysis!B:B,"<"&EDate(A9,1), Analysis!A:A,"rent") -SUMIFS(Analysis!C:C,Analysis!B:B, ">="&A9,Analysis!B:B,"<"&EDate(A9,1), Analysis!A:A,"salaries") -> -845250 | E9: =-SUMIFS(Analysis!C:C, Analysis!E:E,"Expenses", Analysis!B:B, ">="&A9,Analysis!B:B,"<"&EDate(A9,1), Analysis!A:A,"<>Electricity",Analysis!A:A,"<>Petroleum",Analysis!A:A,"<>rent",Analysis!A:A,"<>salaries") -> -9263549 | F9: =B:B +E:E -> 7026258.5 | G9: =F:F + D:D -> 6181008.5 | H9: =(F:F/B:B) -> 0.43132852 | I9: =(G:G/B:B) -> 0.37944024
A10: 45901 | B10: =SUMIFS(Analysis!C:C, Analysis!E:E, "Sales", Analysis!B:B, ">="&A10, Analysis!B:B, "<"&EDATE(A10,1)) -> 14669458 | C10: =SUMIFS(Analysis!C:C, Analysis!E:E, "Expenses", Analysis!B:B, ">="&A10, Analysis!B:B, "<"&EDATE(A10,1)) -> 8603999.8 | D10: =-SUMIFS(Analysis!C:C,Analysis!B:B, ">="&A10,Analysis!B:B,"<"&EDate(A10,1), Analysis!A:A,"Electricity")-SUMIFS(Analysis!C:C,Analysis!B:B, ">="&A10,Analysis!B:B,"<"&EDate(A10,1), Analysis!A:A,"Petroleum") -SUMIFS(Analysis!C:C,Analysis!B:B, ">="&A10,Analysis!B:B,"<"&EDate(A10,1), Analysis!A:A,"rent") -SUMIFS(Analysis!C:C,Analysis!B:B, ">="&A10,Analysis!B:B,"<"&EDate(A10,1), Analysis!A:A,"salaries") -> -845250 | E10: =-SUMIFS(Analysis!C:C, Analysis!E:E,"Expenses", Analysis!B:B, ">="&A10,Analysis!B:B,"<"&EDate(A10,1), Analysis!A:A,"<>Electricity",Analysis!A:A,"<>Petroleum",Analysis!A:A,"<>rent",Analysis!A:A,"<>salaries") -> -7758749.8 | F10: =B:B +E:E -> 6910707.7 | G10: =F:F + D:D -> 6065457.7 | H10: =(F:F/B:B) -> 0.47109497 | I10: =(G:G/B:B) -> 0.41347525
A11: 45931 | B11: =SUMIFS(Analysis!C:C, Analysis!E:E, "Sales", Analysis!B:B, ">="&A11, Analysis!B:B, "<"&EDATE(A11,1)) -> 14669458 | C11: =SUMIFS(Analysis!C:C, Analysis!E:E, "Expenses", Analysis!B:B, ">="&A11, Analysis!B:B, "<"&EDATE(A11,1)) -> 10270132 | D11: =-SUMIFS(Analysis!C:C,Analysis!B:B, ">="&A11,Analysis!B:B,"<"&EDate(A11,1), Analysis!A:A,"Electricity")-SUMIFS(Analysis!C:C,Analysis!B:B, ">="&A11,Analysis!B:B,"<"&EDate(A11,1), Analysis!A:A,"Petroleum") -SUMIFS(Analysis!C:C,Analysis!B:B, ">="&A11,Analysis!B:B,"<"&EDate(A11,1), Analysis!A:A,"rent") -SUMIFS(Analysis!C:C,Analysis!B:B, ">="&A11,Analysis!B:B,"<"&EDate(A11,1), Analysis!A:A,"salaries") -> -937250 | E11: =-SUMIFS(Analysis!C:C, Analysis!E:E,"Expenses", Analysis!B:B, ">="&A11,Analysis!B:B,"<"&EDate(A11,1), Analysis!A:A,"<>Electricity",Analysis!A:A,"<>Petroleum",Analysis!A:A,"<>rent",Analysis!A:A,"<>salaries") -> -9332882.5 | F11: =B:B +E:E -> 5336575 | G11: =F:F + D:D -> 4399325 | H11: =(F:F/B:B) -> 0.36378816 | I11: =(G:G/B:B) -> 0.29989691
A12: 45962 | B12: =SUMIFS(Analysis!C:C, Analysis!E:E, "Sales", Analysis!B:B, ">="&A12, Analysis!B:B, "<"&EDATE(A12,1)) -> 14757145 | C12: =SUMIFS(Analysis!C:C, Analysis!E:E, "Expenses", Analysis!B:B, ">="&A12, Analysis!B:B, "<"&EDATE(A12,1)) -> 11566114 | D12: =-SUMIFS(Analysis!C:C,Analysis!B:B, ">="&A12,Analysis!B:B,"<"&EDate(A12,1), Analysis!A:A,"Electricity")-SUMIFS(Analysis!C:C,Analysis!B:B, ">="&A12,Analysis!B:B,"<"&EDate(A12,1), Analysis!A:A,"Petroleum") -SUMIFS(Analysis!C:C,Analysis!B:B, ">="&A12,Analysis!B:B,"<"&EDate(A12,1), Analysis!A:A,"rent") -SUMIFS(Analysis!C:C,Analysis!B:B, ">="&A12,Analysis!B:B,"<"&EDate(A12,1), Analysis!A:A,"salaries") -> -879750 | E12: =-SUMIFS(Analysis!C:C, Analysis!E:E,"Expenses", Analysis!B:B, ">="&A12,Analysis!B:B,"<"&EDate(A12,1), Analysis!A:A,"<>Electricity",Analysis!A:A,"<>Petroleum",Analysis!A:A,"<>rent",Analysis!A:A,"<>salaries") -> -10686364 | F12: =B:B +E:E -> 4070781.5 | G12: =F:F + D:D -> 3191031.5 | H12: =(F:F/B:B) -> 0.27585156 | I12: =(G:G/B:B) -> 0.21623637
A13: 45992 | B13: =SUMIFS(Analysis!C:C, Analysis!E:E, "Sales", Analysis!B:B, ">="&A13, Analysis!B:B, "<"&EDATE(A13,1)) -> 14110960 | C13: =SUMIFS(Analysis!C:C, Analysis!E:E, "Expenses", Analysis!B:B, ">="&A13, Analysis!B:B, "<"&EDATE(A13,1)) -> 11229462 | D13: =-SUMIFS(Analysis!C:C,Analysis!B:B, ">="&A13,Analysis!B:B,"<"&EDate(A13,1), Analysis!A:A,"Electricity")-SUMIFS(Analysis!C:C,Analysis!B:B, ">="&A13,Analysis!B:B,"<"&EDate(A13,1), Analysis!A:A,"Petroleum") -SUMIFS(Analysis!C:C,Analysis!B:B, ">="&A13,Analysis!B:B,"<"&EDate(A13,1), Analysis!A:A,"rent") -SUMIFS(Analysis!C:C,Analysis!B:B, ">="&A13,Analysis!B:B,"<"&EDate(A13,1), Analysis!A:A,"salaries") -> -874000 | E13: =-SUMIFS(Analysis!C:C, Analysis!E:E,"Expenses", Analysis!B:B, ">="&A13,Analysis!B:B,"<"&EDate(A13,1), Analysis!A:A,"<>Electricity",Analysis!A:A,"<>Petroleum",Analysis!A:A,"<>rent",Analysis!A:A,"<>salaries") -> -10355462 | F13: =B:B +E:E -> 3755497.5 | G13: =F:F + D:D -> 2881497.5 | H13: =(F:F/B:B) -> 0.26614047 | I13: =(G:G/B:B) -> 0.2042028
... A16: 46082 | B16: =SUMIFS(Analysis!C:C, Analysis!E:E, "Sales", Analysis!B:B, ">="&A16, Analysis!B:B, "<"&EDATE(A16,1)) -> 12095872 | C16: =SUMIFS(Analysis!C:C, Analysis!E:E, "Expenses", Analysis!B:B, ">="&A16, Analysis!B:B, "<"&EDATE(A16,1)) -> 7597043.8 | D16: =-SUMIFS(Analysis!C:C,Analysis!B:B, ">="&A16,Analysis!B:B,"<"&EDate(A16,1), Analysis!A:A,"Electricity")-SUMIFS(Analysis!C:C,Analysis!B:B, ">="&A16,Analysis!B:B,"<"&EDate(A16,1), Analysis!A:A,"Petroleum") -SUMIFS(Analysis!C:C,Analysis!B:B, ">="&A16,Analysis!B:B,"<"&EDate(A16,1), Analysis!A:A,"rent") -SUMIFS(Analysis!C:C,Analysis!B:B, ">="&A16,Analysis!B:B,"<"&EDate(A16,1), Analysis!A:A,"salaries") -> -799250 | E16: =-SUMIFS(Analysis!C:C, Analysis!E:E,"Expenses", Analysis!B:B, ">="&A16,Analysis!B:B,"<"&EDate(A16,1), Analysis!A:A,"<>Electricity",Analysis!A:A,"<>Petroleum",Analysis!A:A,"<>rent",Analysis!A:A,"<>salaries") -> -6797793.8 | F16: =B:B +E:E -> 5298078.8 | G16: =F:F + D:D -> 4498828.8 | H16: =(F:F/B:B) -> 0.43800716 | I16: =(G:G/B:B) -> 0.3719309
F17: =SUM(F2:F16) -> 91657455

Sheet Dashboard
A43: SUM of Amount+ | B43: Category
A44: Month - Year-Month | B44: Electricity | C44: Petroleum | D44: Rent | E44: Salaries | F44: Grand Total
A45: 2025-Jan | B45: 46000 | D45: 115000 | E45: 770500 | F45: 931500
A46: 2025-Feb | B46: 46000 | D46: 115000 | E46: 655500 | F46: 816500
A47: 2025-Mar | B47: 46000 | D47: 115000 | E47: 655500 | F47: 816500
A48: 2025-Apr | B48: 57500 | D48: 115000 | E48: 586500 | F48: 759000
A49: 2025-May | B49: 57500 | D49: 115000 | E49: 586500 | F49: 759000
A50: 2025-Jun | B50: 57500 | D50: 115000 | E50: 626750 | F50: 799250
A51: 2025-Jul | B51: 57500 | D51: 115000 | E51: 626750 | F51: 799250
A52: 2025-Aug | B52: 69000 | D52: 115000 | E52: 661250 | F52: 845250
A53: 2025-Sep | B53: 69000 | D53: 115000 | E53: 661250 | F53: 845250
A54: 2025-Oct | B54: 69000 | C54: 57500 | D54: 115000 | E54: 695750 | F54: 937250
A55: 2025-Nov | B55: 69000 | D55: 115000 | E55: 695750 | F55: 879750
A56: 2025-Dec | B56: 57500 | C56: 34500 | D56: 115000 | E56: 667000 | F56: 874000
A57: 2026-Jan | B57: 57500 | C57: 92000 | D57: 115000 | E57: 552000 | F57: 816500
A58: 2026-Feb | B58: 57500 | C58: 34500 | D58: 115000 | E58: 592250 | F58: 799250
A59: 2026-Mar | B59: 57500 | C59: 80500 | D59: 115000 | E59: 546250 | F59: 799250
A60: Grand Total | B60: 874000 | C60: 299000 | D60: 1725000 | E60: 9579500 | F60: 12477500
